{
    "category": "etaireia-psychikon-ereynon",
    "subcategorySlug": "peiramata",
    "subcategory": "'Πειράματα",
    "slug": "etaireia-psychikon-ereynon/peiramata",
    "articles": [

{
            "id": "158",
            "title": "Πειράματα Ραβδοσκοπίας με Μέντιουμ - 1929",
            "slug": "peiramata-ravdoskopias-medium-1929",
            "author": "",
            "date": "1929-11-14",
            "excerpt": "Πειράματα ραβδοσκοπίας με τον αββά Λαμπέρ και μέντιουμ για ανίχνευση νερού στην Κολοκυνθού.",
            "mainArea": "Κολοκυνθού",
            "subLocation": "",
            "locationTags": ["Κολοκυνθού", "Αθήνα"],
            "lat": 37.9838,
            "lng": 23.7275,
            "image": {
              "src": "/images/efimerides/peiramata-ravdoskopias.webp",
              "alt": "Πειράματα Ραβδοσκοπίας με Μέντιουμ"
            },
            "content": [
              {
                "type": "text",
                "value": "Προσπαθούν να βρουν νερό με Μάγια. Τα χθεσινά πειράματα στην Κολοκυνθού."
              },
              {
                "type": "text",
                "value": "Ο Αββας Λαμπερ και η θαυματουργή Ράβδος του."
              },
              {
                "type": "text",
                "value": "Χθες στις 9:30 π.μ ο διάσημος υδροσκόπος αββάς Λαμπέρ, συνοδευόμενος απο τον πρόεδρο των Ψυχικών Ερευνών κ. Τανάγρα, τον Γενικο γραμματέα - νευρολόγο κ. Βλαστό και των Ελλήνων μέντιουμ δεσποινίδων Ελπινικη Αθανασουπούλου, Ανδρονίκη Χαλκιαδάκη, Σοφία Κανά και Ζαχαρία Σουλακιώτη, μετέβησαν στην Κολοκυνθού για να εκτελέσουν πειράματα ραβδοσκοπίας."
              },
              {
                "type": "text",
                "value": "Το σύστημα λειτουργεί με τον εξής τρόπο. Ο υδροσκόπος, ο προικισμένος δηλαδή με την εξαιρετική ιδιότητα να αισθάνεται το νερό, το οποίο υπάρχει μέσα στο έδαφος, κάτω απο τα πόδια του, προχωράει κρατώντας δύο χαλύβδινα ελάσματα, τα οποία κρατάει στο στήθος του, δεμένα μεταξύ τους στο ένα άκρο τους σχηματίζοντας οξεία γωνία. Όταν φτάσει στο μέρος όπου υπάρχει νερό ή κορυφή της γωνίας αρχίζει να κινείται."
              },
              {
                "type": "text",
                "value": "Ο αββάς Λαμπέρ πήγε σε διάφορα μέρη και εξακρίβωσε την ύπαρξη νερού. Οι κάτοικοι της περιοχής, μαθαίνοντας την είδηση, βρέθηκαν στο χώρο για να παρακολουθήσουν τα πειράματα. Σε ένα απο τα σπίτια της περιοχής, κάλεσαν στον Λαμπέρ να εξετάσει αν υπάρχει νερό απο κάτω. Μετά απο εξέταση δεν βρέθηκε νερό."
              },
              {
                "type": "text",
                "value": "Ο αββάς Λαμπέρ, δοκίμασε τα μέντιουμ, τα οποία αναφέρθηκαν πριν, με μικρά αποτελέσματα αλλά ικανοποιητικά, δοθέντος ότι είναι η πρώτη φορά που γίνεται τέτοιου ειδους πείραμα. Απαιτείται συστηματική εκπαίδευση του μέντιουμ ώστε να φτάσει στο σημείο να αισθάνεται με σιγουρία και άμεσα το νερό κάτω απο τη γή."
              },
              {
                "type": "text",
                "value": "Ως εξήγηση του φαινομένου, δίνεται η εξής. Το νερό επιδρά ραδιενεργητικά στο νευρικό σύστημα του μέντιουμ, το οποίο συγκεντρώνεται στο έλασμα το οποίο κρατάει και το οποίο μπορεί να είναι ακόμα και ένα κλαράκι δέντρου και κάνει ασυνείδητα μικρές κινήσεις, οι οποίες αποδίδονται στο έλασμα."
              }
            ],
            "source": "Σκριπ - 14 Νοεμβρίου 1929 (σελ. 4)"
          }
    ],
          "seo": {
        "metaTitle": "Τα Πειράματα της Εταιρίας Ψυχικών Ερευνών | haunted.gr",
        "metaDescription": "Τα πειράματα και οι έρευνες της Εταιρίας Ψυχικών Ερευνών στην Ελλάδα - Αρχείο εφημερίδων 20ου αιώνα",
        "keywords": ["τηλεκίνηση", "ψυχοκίνηση","Πειράματα Πανεπιστημίου", "Άγγελος Τανάγρας", "Εταιρία Ψυχικών Ερευνών", "ψυχικές έρευνες", "πειράματα"],
        "canonical": "https://haunted.gr/etaireia-psychikon-ereynon/erevnes-fainomena/peiramata-psychikon-ereynon-stoicheiomena-spitia-1924",
        "structuredData": {
            "@context": "https://schema.org",
            "@type": "CollectionPage",
            "name": "Έρευνες Φαινομένων - Εταιρία Ψυχικών Ερευνών",
            "description": "Έρευνες και μελέτες  φαινομένων από την Ελληνική Εταιρία Ψυχικών Ερευνών",
            "url": "https://haunted.gr/etaireia-psychikon-ereynon/peiramata",
            "publisher": {
                "@type": "Organization",
                "name": "haunted.gr"
            },
            "mainEntity": [
                {
                    "@type": "Article",
                    "name": "Τα Τηλεκινητικά φαινόμενα της Λαμίας 1929",
                    "url": "https://haunted.gr/etaireia-psychikon-ereynon/erevnes-fainomena/peiramata-psychikon-ereynon-stoicheiomena-spitia-1924",
                    "author": { "@type": "Person", "name": "Εφημερίδα Εμπρος" },
                    "datePublished": "1929-01-11",
                    "description": "Αναφορά τηλεκινητικών φαινομένων και ψυχικών ερευνών στην Λαμία υπό τον Άγγελο Τανάγρα.",
                    "image": "https://haunted.gr/images/efimerides/lamia-telekinesi-1929.webp"
                }
            ]
        }
    }
}